metadater/__init__.py
metadater/exe.py
metadater/git.py
metadater-3.1.1.dist-info/LICENSE
metadater-3.1.1.dist-info/METADATA
metadater-3.1.1.dist-info/WHEEL
metadater-3.1.1.dist-info/entry_points.txt
metadater-3.1.1.dist-info/top_level.txt
metadater-3.1.1.dist-info/RECORD
