Metadata-Version: 2.1
Name: metadater
Version: 3.1.1
Summary: A Python package providing an easy way to get a Windows app's version and other metadata from Git during development or from the executable after freezing.
Home-page: https://github.com/hylkepostma/metadater
Author: Hylke Postma
Author-email: info@hylkepostma.nl
License: MIT
Keywords: python git pefile windows metadata python3
Platform: UNKNOWN
Classifier: Development Status :: 5 - Production/Stable
Classifier: Intended Audience :: Developers
Classifier: Topic :: Software Development :: Build Tools
Classifier: License :: OSI Approved :: MIT License
Classifier: Operating System :: Microsoft :: Windows
Classifier: Programming Language :: Python :: 3.4
Classifier: Programming Language :: Python :: 3.5
Classifier: Programming Language :: Python :: 3.6
Classifier: Programming Language :: Python :: 3.7
Classifier: Programming Language :: Python :: 3.8
Requires-Dist: click
Requires-Dist: pefile (>=2018.8.8)
Requires-Dist: semver
